CONTRIBUTING.md
Dockerfile
LICENSE
README.md
Version.txt
docker-compose.yml
requirements.txt
setup.py
pyfos/__init__.py
pyfos/pyfos_auth.py
pyfos/pyfos_auth_token.py
pyfos/pyfos_brocade_access_gateway.py
pyfos/pyfos_brocade_chassis.py
pyfos/pyfos_brocade_extension.py
pyfos/pyfos_brocade_extension_ip_interface.py
pyfos/pyfos_brocade_extension_ip_route.py
pyfos/pyfos_brocade_extension_ipsec_policy.py
pyfos/pyfos_brocade_extension_tunnel.py
pyfos/pyfos_brocade_fabric.py
pyfos/pyfos_brocade_fabric_traffic_controller.py
pyfos/pyfos_brocade_fdmi.py
pyfos/pyfos_brocade_fibrechannel_configuration.py
pyfos/pyfos_brocade_fibrechannel_diagnostics.py
pyfos/pyfos_brocade_fibrechannel_logical_switch.py
pyfos/pyfos_brocade_fibrechannel_routing.py
pyfos/pyfos_brocade_fibrechannel_switch.py
pyfos/pyfos_brocade_fibrechannel_trunk.py
pyfos/pyfos_brocade_fru.py
pyfos/pyfos_brocade_interface.py
pyfos/pyfos_brocade_license.py
pyfos/pyfos_brocade_lldp.py
pyfos/pyfos_brocade_logging.py
pyfos/pyfos_brocade_maps.py
pyfos/pyfos_brocade_media.py
pyfos/pyfos_brocade_module_version.py
pyfos/pyfos_brocade_name_server.py
pyfos/pyfos_brocade_operation_config.py
pyfos/pyfos_brocade_operation_end_device_management.py
pyfos/pyfos_brocade_operation_extension.py
pyfos/pyfos_brocade_operation_fabric.py
pyfos/pyfos_brocade_operation_firmwarecleaninstall.py
pyfos/pyfos_brocade_operation_firmwaredownload.py
pyfos/pyfos_brocade_operation_license.py
pyfos/pyfos_brocade_operation_lldp.py
pyfos/pyfos_brocade_operation_pcie_health.py
pyfos/pyfos_brocade_operation_show_status.py
pyfos/pyfos_brocade_operation_supportlink.py
pyfos/pyfos_brocade_operation_supportsave.py
pyfos/pyfos_brocade_operation_zone.py
pyfos/pyfos_brocade_security.py
pyfos/pyfos_brocade_snmp.py
pyfos/pyfos_brocade_supportlink.py
pyfos/pyfos_brocade_time.py
pyfos/pyfos_brocade_zone.py
pyfos/pyfos_login.py
pyfos/pyfos_rest_util.py
pyfos/pyfos_type.py
pyfos/pyfos_util.py
pyfos/pyfos_version.py
pyfos/pyfos_vobject.py
pyfos/version.py
pyfos.egg-info/PKG-INFO
pyfos.egg-info/SOURCES.txt
pyfos.egg-info/dependency_links.txt
pyfos.egg-info/not-zip-safe
pyfos.egg-info/requires.txt
pyfos.egg-info/top_level.txt
