Metadata-Version: 2.1
Name: pyfos
Version: 2.0.0
Summary: Brocade FOS Library.
Home-page: http://www.brocade.com/
Author: Brocade Communications Systems LLC.
Author-email: Automation.BSN@broadcom.com
License: UNKNOWN
Platform: UNKNOWN
